odoo/addons/ssi_purchase_stock/README.rst
odoo/addons/ssi_purchase_stock/__init__.py
odoo/addons/ssi_purchase_stock/__manifest__.py
odoo/addons/ssi_purchase_stock/models/__init__.py
odoo/addons/ssi_purchase_stock/models/purchase_order.py
odoo/addons/ssi_purchase_stock/models/purchase_order_line.py
odoo/addons/ssi_purchase_stock/models/res_users.py
odoo/addons/ssi_purchase_stock/models/stock_warehouse.py
odoo/addons/ssi_purchase_stock/security/ir_rule_data.xml
odoo/addons/ssi_purchase_stock/security/res_group_data.xml
odoo/addons/ssi_purchase_stock/static/description/icon.png
odoo/addons/ssi_purchase_stock/views/purchase_order_views.xml
odoo/addons/ssi_purchase_stock/views/stock_warehouse_views.xml
odoo14_addon_ssi_purchase_stock-14.0.1.2.0.dist-info/METADATA
odoo14_addon_ssi_purchase_stock-14.0.1.2.0.dist-info/WHEEL
odoo14_addon_ssi_purchase_stock-14.0.1.2.0.dist-info/top_level.txt
odoo14_addon_ssi_purchase_stock-14.0.1.2.0.dist-info/RECORD
